{"0": [{"ime": "Moltres", "tip": "2", "shiny": "da", "evolucija": "1", "mega": "ne", "legendaren": "da", "žival": "ptič"}, [], null], "1": [{"ime": "Moltres", "tip": "2", "shiny": "da", "evolucija": "1", "mega": "ne", "legendaren": "da", "žival": "ptič"}, [], "W"], "2": [{"ime": "Blastoise", "tip": "1", "shiny": "ne", "evolucija": "3", "mega": "da", "legendaren": "ne", "žival": "želva"}, [], "Z"], "3": [{"ime": "Torkoal", "tip": "1", "shiny": "ne", "evolucija": "1", "mega": "ne", "legendaren": "ne", "žival": "želva"}, [], null], "4": [{"ime": "Rookidee", "tip": "1", "shiny": "ne", "evolucija": "3", "mega": "ne", "legendaren": "ne", "žival": "ptič"}, [], "Z"], "5": [{"ime": "Braviary", "tip": "2", "shiny": "ne", "evolucija": "2", "mega": "ne", "legendaren": "ne", "žival": "ptič"}, [], "Z"], "6": [{"ime": "Mewtwo", "tip": "1", "shiny": "ne", "evolucija": "1", "mega": "da", "legendaren": "da", "žival": "mačka"}, [], "W"], "7": [{"ime": "Combee", "tip": "2", "shiny": "ne", "evolucija": "2", "mega": "ne", "legendaren": "ne", "žival": "čebela"}, [], "Z"], "8": [{"ime": "Wyredeer", "tip": "2", "shiny": "ne", "evolucija": "2", "mega": "ne", "legendaren": "ne", "žival": "jelen"}, [], "Z"], "9": [{"ime": "Combee", "tip": "2", "shiny": "ne", "evolucija": "2", "mega": "ne", "legendaren": "ne", "žival": "čebela"}, [], "Z"], "10": [{"ime": "Moltres", "tip": "2", "shiny": "da", "evolucija": "1", "mega": "ne", "legendaren": "da", "žival": "ptič"}, [], "Z"]}